{"cameraMode":{"drawMode":0,"name":"Shaded","section":"Shading Mode"},"sceneLighting":false,"audioPlay":false,"sceneViewState":{"m_AlwaysRefresh":false,"showFog":true,"showSkybox":false,"showFlares":true,"showImageEffects":true,"showParticleSystems":true,"showVisualEffectGraphs":true,"m_FxEnabled":true},"in2DMode":false,"pivot":{"x":-26.876806259155275,"y":0.35422053933143618,"z":-27.93582534790039},"rotation":{"x":-0.2962258756160736,"y":0.6205443143844605,"z":-0.27326643466949465,"w":-0.6726933717727661},"size":0.8386517763137817,"orthographic":false}